{
  "lastUpdate": "2026-02-25",
  "problemSet": {
    "Integration": {
      "Hard": {
        "id": "int-h-31",
        "date": "2026-02-25T07:07:16.932Z",
        "problemLatex": "The region R is bounded by the curve y = \\sqrt{x}, the x-axis, and the line x = 4. Find the volume of the solid formed when R is rotated 360\\degree about the x-axis.",
        "possibleAnswers": [
          "8pi",
          "8\\pi",
          "25.13",
          "25.132"
        ],
        "fullSolutionLatex": "The volume of a solid of revolution about the x-axis is given by the formula V = \\int_{a}^{b} \\pi y^2 \\, dx.\\\\ Given y = \\sqrt{x}, so y^2 = x.\\\\ The limits of integration are from x = 0 to x = 4 (from the x-axis intersection to the line x=4).\\\\ V = \\int_{0}^{4} \\pi (\\sqrt{x})^2 \\, dx \\\\ V = \\int_{0}^{4} \\pi x \\, dx \\\\ V = \\pi \\left[ \\frac{x^2}{2} \\right]_{0}^{4} \\\\ V = \\pi \\left( \\frac{4^2}{2} - \\frac{0^2}{2} \\right) \\\\ V = \\pi \\left( \\frac{16}{2} - 0 \\right) \\\\ V = 8\\pi \\text{ cubic units}.",
        "hintsLatex": [
          "Recall the formula for the volume of revolution about the x-axis.",
          "Square the function y to get y^2.",
          "Identify the correct limits of integration."
        ],
        "topicsCovered": [
          "Volumes of Revolution (x-axis)"
        ],
        "difficultyLevel": "Hard",
        "problemType": "Integration",
        "funFact": "Calculating volumes of revolution has applications in engineering for designing components like shafts, bottles, and architectural structures."
      },
      "Medium": {
        "id": "int-m-31",
        "date": "2026-02-25T07:07:16.932Z",
        "problemLatex": "Evaluate \\int x(x^2 + 1)^3 \\, dx.",
        "possibleAnswers": [
          "1/8(x^2+1)^4 + C",
          "1/8(x^2+1)^4+C",
          "(x^2+1)^4/8 + C",
          "0.125(x^2+1)^4 + C"
        ],
        "fullSolutionLatex": "This integral can be solved using substitution. Let u = x^2 + 1.\\\\ Then \\frac{du}{dx} = 2x, which means dx = \\frac{du}{2x}.\\\\ Substitute u and dx into the integral:\\\\ \\int x(u)^3 \\left(\\frac{du}{2x}\\right) = \\int \\frac{1}{2} u^3 \\, du \\\\ Now, integrate with respect to u:\\\\ = \\frac{1}{2} \\cdot \\frac{u^{3+1}}{3+1} + C \\\\ = \\frac{1}{2} \\cdot \\frac{u^4}{4} + C \\\\ = \\frac{1}{8} u^4 + C \\\\ Finally, substitute back u = x^2 + 1:\\\\ = \\frac{1}{8}(x^2 + 1)^4 + C.",
        "hintsLatex": [
          "Consider using a substitution. What part of the integrand looks like a good candidate for 'u'?",
          "Remember to also substitute 'dx' in terms of 'du'.",
          "Don't forget to substitute 'u' back to 'x' after integration."
        ],
        "topicsCovered": [
          "Integration by Substitution (u-sub)"
        ],
        "difficultyLevel": "Medium",
        "problemType": "Integration",
        "funFact": "Integration by substitution is often called 'u-substitution' and is the reverse of the chain rule for differentiation."
      },
      "Easy": {
        "id": "int-e-31",
        "date": "2026-02-25T07:07:16.932Z",
        "problemLatex": "Find \\int (3x^2 - 4x + 5) \\, dx.",
        "possibleAnswers": [
          "x^3 - 2x^2 + 5x + C",
          "x^3-2x^2+5x+C",
          "x^3 - 2x^2 + 5x + c",
          "x cubed minus 2x squared plus 5x plus C"
        ],
        "fullSolutionLatex": "To find the indefinite integral, we apply the power rule for integration, \\int x^n \\, dx = \\frac{x^{n+1}}{n+1} + C, to each term.\\\\ \\int (3x^2 - 4x + 5) \\, dx = 3\\frac{x^{2+1}}{2+1} - 4\\frac{x^{1+1}}{1+1} + 5\\frac{x^{0+1}}{0+1} + C \\\\ = 3\\frac{x^3}{3} - 4\\frac{x^2}{2} + 5\\frac{x^1}{1} + C \\\\ = x^3 - 2x^2 + 5x + C.",
        "hintsLatex": [
          "Remember the power rule for integration: \\int x^n \\, dx = \\frac{x^{n+1}}{n+1} + C.",
          "Integrate each term separately.",
          "Don't forget the constant of integration, +C."
        ],
        "topicsCovered": [
          "Indefinite Integrals of Polynomials"
        ],
        "difficultyLevel": "Easy",
        "problemType": "Integration",
        "funFact": "The 'S' shape of the integral sign \\int is an elongated letter 'S', standing for 'sum', as integration is essentially a sum of infinitely many infinitesimal parts."
      }
    },
    "Differentiation": {
      "Hard": {
        "id": "diff-h-31",
        "date": "2026-02-25T07:07:16.932Z",
        "problemLatex": "A rectangular enclosure is to be built with one side against an existing wall. If 120 meters of fencing is available for the other three sides, find the maximum area of the enclosure.",
        "possibleAnswers": [
          "1800 m^2",
          "1800m^2",
          "1800"
        ],
        "fullSolutionLatex": "Let the side parallel to the wall be length L and the two sides perpendicular to the wall be width W.\\\\ The total fencing available is for the three sides: L + 2W = 120.\\\\ From this, L = 120 - 2W.\\\\ The area of the enclosure is A = LW.\\\\ Substitute L: A = (120 - 2W)W = 120W - 2W^2.\\\\ To find the maximum area, differentiate A with respect to W and set the derivative to zero.\\\\ \\frac{dA}{dW} = 120 - 4W.\\\\ Set \\frac{dA}{dW} = 0:\\\\ 120 - 4W = 0 \\\\ 4W = 120 \\\\ W = 30 \\text{ meters}.\\\\ Now, find L using W = 30:\\\\ L = 120 - 2(30) = 120 - 60 = 60 \\text{ meters}.\\\\ The maximum area is A = LW = 60 \\times 30 = 1800 \\text{ m}^2.\\\\ To confirm it's a maximum, find the second derivative: \\frac{d^2A}{dW^2} = -4. Since this is negative, it confirms a maximum.",
        "hintsLatex": [
          "Define variables for the dimensions of the rectangle.",
          "Formulate an equation for the total fencing used.",
          "Express the area as a function of a single variable, then differentiate and set to zero."
        ],
        "topicsCovered": [
          "Optimization Problems"
        ],
        "difficultyLevel": "Hard",
        "problemType": "Differentiation",
        "funFact": "Optimization problems using differentiation are crucial in fields like economics (maximizing profit), engineering (minimizing material usage), and logistics (optimizing routes)."
      },
      "Medium": {
        "id": "diff-m-31",
        "date": "2026-02-25T07:07:16.932Z",
        "problemLatex": "A curve is defined parametrically by x = t^2 + 1 and y = 2t^3 - t. Find \\frac{dy}{dx} in terms of t.",
        "possibleAnswers": [
          "(6t^2-1)/(2t)",
          "(6t^2-1)/(2t)",
          "6t^2-1 / 2t"
        ],
        "fullSolutionLatex": "To find \\frac{dy}{dx} for parametric equations, we use the formula \\frac{dy}{dx} = \\frac{dy/dt}{dx/dt}.\\\\ First, differentiate x with respect to t:\\\\ \\frac{dx}{dt} = \\frac{d}{dt}(t^2 + 1) = 2t.\\\\ Next, differentiate y with respect to t:\\\\ \\frac{dy}{dt} = \\frac{d}{dt}(2t^3 - t) = 6t^2 - 1.\\\\ Now, apply the formula:\\\\ \\frac{dy}{dx} = \\frac{6t^2 - 1}{2t}.",
        "hintsLatex": [
          "Recall the formula for parametric differentiation.",
          "Differentiate x with respect to t.",
          "Differentiate y with respect to t."
        ],
        "topicsCovered": [
          "Parametric Differentiation"
        ],
        "difficultyLevel": "Medium",
        "problemType": "Differentiation",
        "funFact": "Parametric equations are useful for describing motion, where 't' often represents time, allowing us to track position (x, y) over time."
      },
      "Easy": {
        "id": "diff-e-31",
        "date": "2026-02-25T07:07:16.932Z",
        "problemLatex": "Differentiate y = (2x+3)^4 with respect to x.",
        "possibleAnswers": [
          "8(2x+3)^3",
          "8(2x+3)^3",
          "8(2x+3)^3"
        ],
        "fullSolutionLatex": "To differentiate y = (2x+3)^4, we use the chain rule.\\\\ Let u = 2x+3. Then y = u^4.\\\\ \\frac{dy}{du} = 4u^3.\\\\ \\frac{du}{dx} = 2.\\\\ By the chain rule, \\frac{dy}{dx} = \\frac{dy}{du} \\cdot \\frac{du}{dx}.\\\\ \\frac{dy}{dx} = 4u^3 \\cdot 2 \\\\ \\frac{dy}{dx} = 8u^3 \\\\ Substitute u = 2x+3 back into the expression:\\\\ \\frac{dy}{dx} = 8(2x+3)^3.",
        "hintsLatex": [
          "Identify the 'inner' and 'outer' functions.",
          "Apply the chain rule: \\frac{dy}{dx} = \\frac{dy}{du} \\cdot \\frac{du}{dx}.",
          "Remember to multiply by the derivative of the inner function."
        ],
        "topicsCovered": [
          "Chain Rule"
        ],
        "difficultyLevel": "Easy",
        "problemType": "Differentiation",
        "funFact": "The chain rule is fundamental in calculus and allows us to differentiate composite functions, which are functions within functions."
      }
    },
    "Further Math (9231)": {
      "Hard": {
        "id": "fm-h-31",
        "date": "2026-02-25T07:07:16.932Z",
        "problemLatex": "Find the eigenvalues of the matrix \\mathbf{A} = \\begin{pmatrix} 2 & 1 \\\\ 1 & 2 \\end{pmatrix}.",
        "possibleAnswers": [
          "1, 3",
          "3, 1",
          "lambda=1,3",
          "lambda=3,1"
        ],
        "fullSolutionLatex": "To find the eigenvalues (\\lambda) of a matrix \\mathbf{A}, we solve the characteristic equation det(\\mathbf{A} - \\lambda\\mathbf{I}) = 0, where \\mathbf{I} is the identity matrix.\\\\ \\mathbf{A} - \\lambda\\mathbf{I} = \\begin{pmatrix} 2 & 1 \\\\ 1 & 2 \\end{pmatrix} - \\lambda\\begin{pmatrix} 1 & 0 \\\\ 0 & 1 \\end{pmatrix} = \\begin{pmatrix} 2-\\lambda & 1 \\\\ 1 & 2-\\lambda \\end{pmatrix}.\\\\ Now, find the determinant:\\\\ det(\\mathbf{A} - \\lambda\\mathbf{I}) = (2-\\lambda)(2-\\lambda) - (1)(1) = 0 \\\\ (2-\\lambda)^2 - 1 = 0 \\\\ 4 - 4\\lambda + \\lambda^2 - 1 = 0 \\\\ \\lambda^2 - 4\\lambda + 3 = 0.\\\\ Factorize the quadratic equation:\\\\ (\\lambda - 1)(\\lambda - 3) = 0.\\\\ Thus, the eigenvalues are \\lambda = 1 and \\lambda = 3.",
        "hintsLatex": [
          "Formulate the characteristic equation det(\\mathbf{A} - \\lambda\\mathbf{I}) = 0.",
          "Calculate the determinant of the resulting matrix.",
          "Solve the quadratic equation for \\lambda."
        ],
        "topicsCovered": [
          "Matrices",
          "Eigenvalues and Eigenvectors"
        ],
        "difficultyLevel": "Hard",
        "problemType": "Further Math (9231)",
        "funFact": "Eigenvalues and eigenvectors are fundamental concepts in linear algebra, used in Google's PageRank algorithm, quantum mechanics, and analyzing vibrations of structures."
      },
      "Medium": {
        "id": "fm-m-31",
        "date": "2026-02-25T07:07:16.932Z",
        "problemLatex": "Use De Moivre's Theorem to express (\\cos \\theta + i \\sin \\theta)^4 in the form x + iy.",
        "possibleAnswers": [
          "cos(4theta) + i sin(4theta)",
          "cos(4\\theta)+isin(4\\theta)",
          "cos4theta + isin4theta"
        ],
        "fullSolutionLatex": "De Moivre's Theorem states that (\\cos \\theta + i \\sin \\theta)^n = \\cos(n\\theta) + i \\sin(n\\theta).\\\\ In this problem, n = 4.\\\\ Therefore, (\\cos \\theta + i \\sin \\theta)^4 = \\cos(4\\theta) + i \\sin(4\\theta).",
        "hintsLatex": [
          "Recall the statement of De Moivre's Theorem.",
          "Identify the value of 'n' in the given expression.",
          "Apply the theorem directly."
        ],
        "topicsCovered": [
          "De Moivre’s Theorem"
        ],
        "difficultyLevel": "Medium",
        "problemType": "Further Math (9231)",
        "funFact": "De Moivre's Theorem, named after Abraham de Moivre, is crucial for finding powers and roots of complex numbers and has applications in trigonometry and polynomial theory."
      },
      "Easy": {
        "id": "fm-e-31",
        "date": "2026-02-25T07:07:16.932Z",
        "problemLatex": "Given z_1 = 3 + 2i and z_2 = 1 - 4i, find z_1z_2.",
        "possibleAnswers": [
          "11 - 10i",
          "11-10i",
          "11 minus 10i"
        ],
        "fullSolutionLatex": "To multiply two complex numbers, we treat them like binomials:\\\\ z_1z_2 = (3 + 2i)(1 - 4i) \\\\ = 3(1) + 3(-4i) + 2i(1) + 2i(-4i) \\\\ = 3 - 12i + 2i - 8i^2.\\\\ Remember that i^2 = -1.\\\\ = 3 - 10i - 8(-1) \\\\ = 3 - 10i + 8 \\\\ = 11 - 10i.",
        "hintsLatex": [
          "Treat complex numbers like binomials when multiplying.",
          "Remember to distribute each term.",
          "Substitute i^2 = -1 and simplify."
        ],
        "topicsCovered": [
          "Complex Numbers (Basic Operations)"
        ],
        "difficultyLevel": "Easy",
        "problemType": "Further Math (9231)",
        "funFact": "Complex numbers, initially met with skepticism, are now indispensable in electrical engineering (AC circuits), quantum mechanics, and signal processing."
      }
    },
    "Mathematics (9709)": {
      "Hard": {
        "id": "math-h-31",
        "date": "2026-02-25T07:07:16.932Z",
        "problemLatex": "Given vectors \\mathbf{a} = 2\\mathbf{i} - \\mathbf{j} + 3\\mathbf{k} and \\mathbf{b} = \\mathbf{i} + 5\\mathbf{j} - 2\\mathbf{k}, find the angle between \\mathbf{a} and \\mathbf{b} to one decimal place.",
        "possibleAnswers": [
          "115.9 degrees",
          "115.9 deg",
          "115.9\\degree"
        ],
        "fullSolutionLatex": "The angle \\theta between two vectors \\mathbf{a} and \\mathbf{b} can be found using the scalar product formula: \\mathbf{a} \\cdot \\mathbf{b} = |\\mathbf{a}||\\mathbf{b}|\\cos\\theta.\\\\ First, calculate the scalar product \\mathbf{a} \\cdot \\mathbf{b}:\\\\ \\mathbf{a} \\cdot \\mathbf{b} = (2)(1) + (-1)(5) + (3)(-2) \\\\ = 2 - 5 - 6 \\\\ = -9.\\\\ Next, calculate the magnitudes of \\mathbf{a} and \\mathbf{b}:\\\\ |\\mathbf{a}| = \\sqrt{2^2 + (-1)^2 + 3^2} = \\sqrt{4 + 1 + 9} = \\sqrt{14}.\\\\ |\\mathbf{b}| = \\sqrt{1^2 + 5^2 + (-2)^2} = \\sqrt{1 + 25 + 4} = \\sqrt{30}.\\\\ Now, use the formula for \\cos\\theta:\\\\ \\cos\\theta = \\frac{\\mathbf{a} \\cdot \\mathbf{b}}{|\\mathbf{a}||\\mathbf{b}|} = \\frac{-9}{\\sqrt{14}\\sqrt{30}} = \\frac{-9}{\\sqrt{420}}.\\\\ \\theta = \\cos^{-1}\\left(\\frac{-9}{\\sqrt{420}}\\right) \\\\ \\theta \\approx 115.9\\degree \\text{ (to one decimal place)}.",
        "hintsLatex": [
          "Recall the scalar product formula: \\mathbf{a} \\cdot \\mathbf{b} = |\\mathbf{a}||\\mathbf{b}|\\cos\\theta.",
          "Calculate the dot product of the two vectors.",
          "Calculate the magnitude of each vector."
        ],
        "topicsCovered": [
          "Vectors in 3D",
          "Scalar Product"
        ],
        "difficultyLevel": "Hard",
        "problemType": "Mathematics (9709)",
        "funFact": "The scalar product (or dot product) of two vectors gives a scalar value and is related to the projection of one vector onto another, finding wide use in physics for concepts like work done."
      },
      "Medium": {
        "id": "math-m-31",
        "date": "2026-02-25T07:07:16.932Z",
        "problemLatex": "Find the first three terms in the expansion of (1 + 2x)^{1/2} in ascending powers of x.",
        "possibleAnswers": [
          "1 + x - 1/2x^2",
          "1+x-0.5x^2",
          "1 + x - 0.5x^2"
        ],
        "fullSolutionLatex": "We use the binomial expansion for a fractional index: \\\\ (1+u)^n = 1 + nu + \\frac{n(n-1)}{2!}u^2 + \\dots \\\\ Here, u = 2x and n = \\frac{1}{2}.\\\\ First term: 1\\\\ Second term: nu = \\frac{1}{2}(2x) = x.\\\\ Third term: \\frac{n(n-1)}{2!}u^2 = \\frac{\\frac{1}{2}(\\frac{1}{2}-1)}{2 \\times 1}(2x)^2 \\\\ = \\frac{\\frac{1}{2}(-\\frac{1}{2})}{2}(4x^2) \\\\ = \\frac{-\\frac{1}{4}}{2}(4x^2) \\\\ = -\\frac{1}{8}(4x^2) \\\\ = -\\frac{1}{2}x^2.\\\\ So, the first three terms are 1 + x - \\frac{1}{2}x^2.",
        "hintsLatex": [
          "Recall the binomial expansion formula for (1+u)^n.",
          "Identify 'n' and 'u' correctly.",
          "Calculate each term up to the x^2 term."
        ],
        "topicsCovered": [
          "Binomial Expansion (Fractional Index)"
        ],
        "difficultyLevel": "Medium",
        "problemType": "Mathematics (9709)",
        "funFact": "The binomial theorem for fractional and negative indices was generalized by Isaac Newton, extending its utility beyond positive integer powers."
      },
      "Easy": {
        "id": "math-e-31",
        "date": "2026-02-25T07:07:16.932Z",
        "problemLatex": "Express x^2 - 6x + 11 in the form (x+a)^2 + b.",
        "possibleAnswers": [
          "(x-3)^2 + 2",
          "(x-3)^2+2",
          "x-3 squared plus 2"
        ],
        "fullSolutionLatex": "To express x^2 - 6x + 11 in the form (x+a)^2 + b, we complete the square.\\\\ The general form is (x+a)^2 + b = x^2 + 2ax + a^2 + b.\\\\ Comparing x^2 - 6x + 11 with x^2 + 2ax + a^2 + b:\\\\ First, compare the coefficient of x: 2a = -6 \\implies a = -3.\\\\ Now, substitute a = -3 into (x+a)^2 + b: (x-3)^2 + b = x^2 - 6x + 9 + b.\\\\ Comparing the constant terms: 9 + b = 11 \\implies b = 2.\\\\ So, x^2 - 6x + 11 = (x-3)^2 + 2.",
        "hintsLatex": [
          "Halve the coefficient of x to find 'a'.",
          "Square 'a' and subtract it to balance the equation.",
          "Then add the original constant term."
        ],
        "topicsCovered": [
          "Quadratic Functions",
          "Completing the Square"
        ],
        "difficultyLevel": "Easy",
        "problemType": "Mathematics (9709)",
        "funFact": "Completing the square is not just for solving quadratics; it's also used to find the vertex of a parabola, which represents the maximum or minimum point of the quadratic function."
      }
    },
    "Further Mechanics (9231)": {
      "Hard": {
        "id": "fmech-h-31",
        "date": "2026-02-25T07:07:16.932Z",
        "problemLatex": "A particle of mass 2 kg moving at velocity \\mathbf{v}_1 = (3\\mathbf{i} + 2\\mathbf{j}) \\text{ m/s} collides with a particle of mass 1 kg moving at velocity \\mathbf{v}_2 = (-2\\mathbf{i} + 4\\mathbf{j}) \\text{ m/s}. If they coalesce, find the velocity of the combined mass.",
        "possibleAnswers": [
          "(4/3 i + 8/3 j) m/s",
          "(4i/3 + 8j/3) m/s",
          "(1.33i + 2.67j) m/s",
          "4/3i + 8/3j",
          "1.33i+2.67j"
        ],
        "fullSolutionLatex": "This is a collision problem where particles coalesce, meaning it's an inelastic collision and momentum is conserved.\\\\ Let m_1 = 2 \\text{ kg}, \\mathbf{v}_1 = (3\\mathbf{i} + 2\\mathbf{j}) \\text{ m/s}.\\\\ Let m_2 = 1 \\text{ kg}, \\mathbf{v}_2 = (-2\\mathbf{i} + 4\\mathbf{j}) \\text{ m/s}.\\\\ Let \\mathbf{V} be the velocity of the combined mass (m_1 + m_2) after collision.\\\\ By conservation of momentum:\\\\ m_1\\mathbf{v}_1 + m_2\\mathbf{v}_2 = (m_1 + m_2)\\mathbf{V}.\\\\ (2)(3\\mathbf{i} + 2\\mathbf{j}) + (1)(-2\\mathbf{i} + 4\\mathbf{j}) = (2 + 1)\\mathbf{V}.\\\\ (6\\mathbf{i} + 4\\mathbf{j}) + (-2\\mathbf{i} + 4\\mathbf{j}) = 3\\mathbf{V}.\\\\ (6-2)\\mathbf{i} + (4+4)\\mathbf{j} = 3\\mathbf{V}.\\\\ 4\\mathbf{i} + 8\\mathbf{j} = 3\\mathbf{V}.\\\\ \\mathbf{V} = \\frac{1}{3}(4\\mathbf{i} + 8\\mathbf{j}) \\text{ m/s} \\\\ \\mathbf{V} = \\left(\\frac{4}{3}\\mathbf{i} + \\frac{8}{3}\\mathbf{j}\\right) \\text{ m/s}.",
        "hintsLatex": [
          "Recall the principle of conservation of momentum for collisions.",
          "Remember that momentum is a vector quantity, so handle i and j components separately.",
          "The combined mass after coalescing is the sum of the individual masses."
        ],
        "topicsCovered": [
          "Impulse and Momentum (Advanced)",
          "Collisions in Two Dimensions"
        ],
        "difficultyLevel": "Hard",
        "problemType": "Further Mechanics (9231)",
        "funFact": "The conservation of momentum is one of the most fundamental laws in physics, applicable from billiard ball collisions to astrophysical events like galaxy mergers."
      },
      "Medium": {
        "id": "fmech-m-31",
        "date": "2026-02-25T07:07:16.932Z",
        "problemLatex": "A particle undergoes Simple Harmonic Motion (SHM) with an amplitude of 0.1 m and a period of \\frac{\\pi}{2} seconds. Find the maximum speed of the particle.",
        "possibleAnswers": [
          "0.4 m/s",
          "0.4m/s",
          "0.4",
          "2/5 m/s"
        ],
        "fullSolutionLatex": "For SHM, the angular frequency \\omega is related to the period T by the formula \\omega = \\frac{2\\pi}{T}.\\\\ Given T = \\frac{\\pi}{2} s.\\\\ \\omega = \\frac{2\\pi}{\\frac{\\pi}{2}} = 2\\pi \\cdot \\frac{2}{\\pi} = 4 \\text{ rad/s}.\\\\ The maximum speed (v_{max}) of a particle in SHM is given by v_{max} = A\\omega.\\\\ Given Amplitude (A) = 0.1 m.\\\\ v_{max} = (0.1)(4) \\\\ v_{max} = 0.4 \\text{ m/s}.",
        "hintsLatex": [
          "First, calculate the angular frequency (\\omega) from the given period.",
          "Recall the formula for maximum speed in SHM.",
          "Substitute the amplitude and angular frequency to find the maximum speed."
        ],
        "topicsCovered": [
          "Simple Harmonic Motion"
        ],
        "difficultyLevel": "Medium",
        "problemType": "Further Mechanics (9231)",
        "funFact": "Simple Harmonic Motion describes many oscillating systems, from pendulums and mass-spring systems to the vibrations of atoms in a crystal lattice."
      },
      "Easy": {
        "id": "fmech-e-31",
        "date": "2026-02-25T07:07:16.932Z",
        "problemLatex": "A particle of mass 0.5 kg moves in a horizontal circle of radius 2m with a constant speed of 4 m/s. Calculate the centripetal force acting on the particle.",
        "possibleAnswers": [
          "4 N",
          "4N",
          "4 Newton",
          "4.0 N"
        ],
        "fullSolutionLatex": "The formula for centripetal force (F_c) is F_c = \\frac{mv^2}{r}.\\\\ Given: \\\\ Mass (m) = 0.5 kg \\\\ Speed (v) = 4 m/s \\\\ Radius (r) = 2 m \\\\ Substitute the values into the formula:\\\\ F_c = \\frac{(0.5)(4^2)}{2} \\\\ F_c = \\frac{(0.5)(16)}{2} \\\\ F_c = \\frac{8}{2} \\\\ F_c = 4 \\text{ N}.",
        "hintsLatex": [
          "Recall the formula for centripetal force.",
          "Identify the given values for mass, speed, and radius.",
          "Substitute the values carefully into the formula."
        ],
        "topicsCovered": [
          "Motion in a Circle",
          "Centripetal Force"
        ],
        "difficultyLevel": "Easy",
        "problemType": "Further Mechanics (9231)",
        "funFact": "Centripetal force is not a new type of force; it's the net force required to keep an object moving in a circular path, often provided by tension, gravity, or friction."
      }
    },
    "Mechanics (9701)": {
      "Hard": {
        "id": "mech-h-31",
        "date": "2026-02-25T07:07:16.932Z",
        "problemLatex": "A particle is moved along the x-axis from x = 1 to x = 3 by a force \\mathbf{F} = (3x^2 - 2x) \\mathbf{i} \\, N. Calculate the work done by the force.",
        "possibleAnswers": [
          "18 J",
          "18J",
          "18 Joules",
          "18.0 J"
        ],
        "fullSolutionLatex": "The work done (W) by a variable force \\mathbf{F}(x) moving an object from x_1 to x_2 is given by the integral W = \\int_{x_1}^{x_2} F(x) \\, dx.\\\\ Given force F(x) = 3x^2 - 2x.\\\\ Limits are x_1 = 1 and x_2 = 3.\\\\ W = \\int_{1}^{3} (3x^2 - 2x) \\, dx.\\\\ Integrate the expression:\\\\ W = \\left[ \\frac{3x^3}{3} - \\frac{2x^2}{2} \\right]_{1}^{3} \\\\ W = \\left[ x^3 - x^2 \\right]_{1}^{3}.\\\\ Now, evaluate at the limits:\\\\ W = (3^3 - 3^2) - (1^3 - 1^2) \\\\ W = (27 - 9) - (1 - 1) \\\\ W = 18 - 0 \\\\ W = 18 \\text{ J}.",
        "hintsLatex": [
          "Recall that work done by a variable force is calculated using integration.",
          "Set up the definite integral with the given force function and limits.",
          "Evaluate the definite integral."
        ],
        "topicsCovered": [
          "Work Done by a Force",
          "Applications to Physics"
        ],
        "difficultyLevel": "Hard",
        "problemType": "Mechanics (9701)",
        "funFact": "In physics, work is not just any effort; it's specifically the energy transferred to or from an object by applying a force that causes displacement, and it's a scalar quantity."
      },
      "Medium": {
        "id": "mech-m-31",
        "date": "2026-02-25T07:07:16.932Z",
        "problemLatex": "Two particles of masses 3 kg and 2 kg are connected by a light inextensible string passing over a smooth fixed pulley. The system is released from rest. Find the acceleration of the 3 kg particle. (Take g = 9.8 m/s^2).",
        "possibleAnswers": [
          "1.96 m/s^2",
          "1.96m/s^2",
          "1.96",
          "9.8/5 m/s^2"
        ],
        "fullSolutionLatex": "Let m_1 = 3 \\text{ kg} and m_2 = 2 \\text{ kg}. Let T be the tension in the string and a be the acceleration of the system.\\\\ For the 3 kg particle (moving downwards):\\\\ F_{net} = m_1g - T = m_1a \\\\ 3(9.8) - T = 3a \\quad (1)\\\\ For the 2 kg particle (moving upwards):\\\\ F_{net} = T - m_2g = m_2a \\\\ T - 2(9.8) = 2a \\quad (2)\\\\ Add (1) and (2) to eliminate T:\\\\ (3(9.8) - T) + (T - 2(9.8)) = 3a + 2a \\\\ 3(9.8) - 2(9.8) = 5a \\\\ (3-2)(9.8) = 5a \\\\ 1(9.8) = 5a \\\\ 9.8 = 5a \\\\ a = \\frac{9.8}{5} \\\\ a = 1.96 \\text{ m/s}^2.\\\\ The 3 kg particle accelerates downwards at 1.96 m/s^2.",
        "hintsLatex": [
          "Draw free-body diagrams for both particles.",
          "Formulate Newton's Second Law (F=ma) equations for each particle, considering their directions of motion.",
          "Solve the simultaneous equations to find the acceleration."
        ],
        "topicsCovered": [
          "Connected Particles",
          "Newton’s Laws"
        ],
        "difficultyLevel": "Medium",
        "problemType": "Mechanics (9701)",
        "funFact": "Atwood machines, which this problem resembles, were originally invented to demonstrate Newton's laws of motion and measure the acceleration due to gravity with high precision."
      },
      "Easy": {
        "id": "mech-e-31",
        "date": "2026-02-25T07:07:16.932Z",
        "problemLatex": "A block of mass 5 kg rests on a horizontal surface. A horizontal force of 20 N is applied to the block. If the coefficient of friction between the block and the surface is 0.3, calculate the acceleration of the block. (Take g = 10 m/s^2).",
        "possibleAnswers": [
          "1 m/s^2",
          "1m/s^2",
          "1.0 m/s^2"
        ],
        "fullSolutionLatex": "First, calculate the frictional force (F_f).\\\\ The normal reaction force (R) on a horizontal surface is equal to the weight of the block, R = mg.\\\\ R = 5 \\text{ kg} \\times 10 \\text{ m/s}^2 = 50 \\text{ N}.\\\\ The maximum static frictional force is F_f = \\mu R.\\\\ F_f = 0.3 \\times 50 = 15 \\text{ N}.\\\\ Since the applied force (20 N) is greater than the maximum frictional force (15 N), the block will accelerate.\\\\ Apply Newton's Second Law, F_{net} = ma.\\\\ F_{applied} - F_f = ma.\\\\ 20 - 15 = 5a.\\\\ 5 = 5a.\\\\ a = 1 \\text{ m/s}^2.",
        "hintsLatex": [
          "Draw a free-body diagram for the block.",
          "Calculate the normal reaction force and then the frictional force.",
          "Apply Newton's Second Law (F=ma) to find the acceleration."
        ],
        "topicsCovered": [
          "Forces and Newton’s Laws",
          "Friction"
        ],
        "difficultyLevel": "Easy",
        "problemType": "Mechanics (9701)",
        "funFact": "Friction, while often seen as a force to overcome, is essential for many everyday activities, allowing us to walk, drive cars, and write with pencils."
      }
    }
  }
}